boltspy/__init__.py
boltspy/repo_tools.py
boltspy/bolttools/__init__.py
boltspy/bolttools/blt.py
boltspy/bolttools/common.py
boltspy/bolttools/drawings.py
boltspy/bolttools/errors.py
boltspy/bolttools/freecad.py
boltspy/bolttools/openscad.py
boltspy/bolttools/pythonpackage.py
boltspy/bolttools/solidworks.py
boltspy/bolttools/statistics.py
boltspy/bolttools/test_blt.py
boltspy/bolttools/test_common.py
boltspy/bolttools/yaml_blt_loader.py
boltspy/bolttools/yaml_in_yaml.py
boltspy-0.4.1.dist-info/LICENSE
boltspy-0.4.1.dist-info/METADATA
boltspy-0.4.1.dist-info/WHEEL
boltspy-0.4.1.dist-info/top_level.txt
boltspy-0.4.1.dist-info/RECORD
