Metadata-Version: 2.1
Name: boltspy
Version: 0.4.1
Summary: BOLTS Open Library for Technical Specifications
Home-page: http://www.boltsparts.org/
Author: Bernd Hahnebach
Author-email: bernd@bimstatik.org
License: UNKNOWN
Platform: UNKNOWN
Classifier: Programming Language :: Python :: 3
Classifier: Operating System :: OS Independent
Requires-Python: >=3.6
License-File: LICENSE
